[
  {
    "id": "1l3c8i22e",
    "url": "photos/江苏天平山/6838ae51b8e3a53bf97a1220224ad4d3.jpg",
    "thumb": "thumbs/江苏天平山/6838ae51b8e3a53bf97a1220224ad4d3.jpg",
    "name": "6838ae51b8e3a53bf97a1220224ad4d3.jpg",
    "category": "江苏天平山",
    "date": "2025-12-11T12:24:53.063Z",
    "size": "561.19 KB",
    "width": 0,
    "height": 0,
    "exif": {}
  },
  {
    "id": "y8fzjc272",
    "url": "photos/江苏天平山/8c1c78702141682a003b7ca2f4bfe3f1.jpg",
    "thumb": "thumbs/江苏天平山/8c1c78702141682a003b7ca2f4bfe3f1.jpg",
    "name": "8c1c78702141682a003b7ca2f4bfe3f1.jpg",
    "category": "江苏天平山",
    "date": "2025-12-11T12:24:51.929Z",
    "size": "154.91 KB",
    "width": 0,
    "height": 0,
    "exif": {}
  },
  {
    "id": "72rigsc25",
    "url": "photos/江苏天平山/42975d8ddaa05e7d6d5560196301c8d8.jpg",
    "thumb": "thumbs/江苏天平山/42975d8ddaa05e7d6d5560196301c8d8.jpg",
    "name": "42975d8ddaa05e7d6d5560196301c8d8.jpg",
    "category": "江苏天平山",
    "date": "2025-12-11T12:24:50.572Z",
    "size": "269.52 KB",
    "width": 0,
    "height": 0,
    "exif": {}
  },
  {
    "id": "burat7jnb",
    "url": "photos/江苏天平山/7b3cfd3e05597b31c66829683a50a8d3.jpg",
    "thumb": "thumbs/江苏天平山/7b3cfd3e05597b31c66829683a50a8d3.jpg",
    "name": "7b3cfd3e05597b31c66829683a50a8d3.jpg",
    "category": "江苏天平山",
    "date": "2025-12-11T12:24:48.208Z",
    "size": "582.82 KB",
    "width": 0,
    "height": 0,
    "exif": {}
  },
  {
    "id": "cafbgx1lq",
    "url": "photos/江苏天平山/5e45f13e83b32a9835565745e4cf30d6.jpg",
    "thumb": "thumbs/江苏天平山/5e45f13e83b32a9835565745e4cf30d6.jpg",
    "name": "5e45f13e83b32a9835565745e4cf30d6.jpg",
    "category": "江苏天平山",
    "date": "2025-12-11T12:24:47.322Z",
    "size": "317.32 KB",
    "width": 0,
    "height": 0,
    "exif": {}
  },
  {
    "id": "pfn0qkpjr",
    "url": "photos/江苏天平山/492b9fc1ff24d78600d2541803ef992d.jpg",
    "thumb": "thumbs/江苏天平山/492b9fc1ff24d78600d2541803ef992d.jpg",
    "name": "492b9fc1ff24d78600d2541803ef992d.jpg",
    "category": "江苏天平山",
    "date": "2025-12-11T12:24:46.156Z",
    "size": "211.03 KB",
    "width": 0,
    "height": 0,
    "exif": {}
  },
  {
    "id": "ar7nfd6nu",
    "url": "photos/江苏天平山/a02a6b188c015bc1d0d96cbabd3cf63c.jpg",
    "thumb": "thumbs/江苏天平山/a02a6b188c015bc1d0d96cbabd3cf63c.jpg",
    "name": "a02a6b188c015bc1d0d96cbabd3cf63c.jpg",
    "category": "江苏天平山",
    "date": "2025-12-11T12:24:44.389Z",
    "size": "585.75 KB",
    "width": 0,
    "height": 0,
    "exif": {}
  },
  {
    "id": "dnrilkxyf",
    "url": "photos/江苏天平山/c720a5c1000a9b9c67b9833583ef5fc8.jpg",
    "thumb": "thumbs/江苏天平山/c720a5c1000a9b9c67b9833583ef5fc8.jpg",
    "name": "c720a5c1000a9b9c67b9833583ef5fc8.jpg",
    "category": "江苏天平山",
    "date": "2025-12-11T12:24:43.508Z",
    "size": "98.05 KB",
    "width": 0,
    "height": 0,
    "exif": {}
  },
  {
    "id": "dh473xqhr",
    "url": "photos/江苏天平山/7c68c616dc05c27b1024b406448f9bab.jpg",
    "thumb": "thumbs/江苏天平山/7c68c616dc05c27b1024b406448f9bab.jpg",
    "name": "7c68c616dc05c27b1024b406448f9bab.jpg",
    "category": "江苏天平山",
    "date": "2025-12-11T12:24:42.486Z",
    "size": "272.45 KB",
    "width": 0,
    "height": 0,
    "exif": {}
  },
  {
    "id": "m7swt8up4",
    "url": "photos/江苏天平山/80f0829880a05598e6d675a4ea2c9bd8.jpg",
    "thumb": "thumbs/江苏天平山/80f0829880a05598e6d675a4ea2c9bd8.jpg",
    "name": "80f0829880a05598e6d675a4ea2c9bd8.jpg",
    "category": "江苏天平山",
    "date": "2025-12-11T12:24:41.290Z",
    "size": "257.22 KB",
    "width": 0,
    "height": 0,
    "exif": {}
  },
  {
    "id": "6r8yjo5ow",
    "url": "photos/浙江大明山/fce6985b75ef561f47aa79ad6a379916.jpg",
    "thumb": "thumbs/浙江大明山/fce6985b75ef561f47aa79ad6a379916.jpg",
    "name": "fce6985b75ef561f47aa79ad6a379916.jpg",
    "category": "浙江大明山",
    "date": "2025-12-11T12:21:36.782Z",
    "size": "129.24 KB",
    "width": 0,
    "height": 0,
    "exif": {}
  },
  {
    "id": "v4t9w4rae",
    "url": "photos/浙江大明山/d7d8d3c033ed7065467f7786639dcb5e.jpg",
    "thumb": "thumbs/浙江大明山/d7d8d3c033ed7065467f7786639dcb5e.jpg",
    "name": "d7d8d3c033ed7065467f7786639dcb5e.jpg",
    "category": "浙江大明山",
    "date": "2025-12-11T12:21:35.697Z",
    "size": "135.79 KB",
    "width": 0,
    "height": 0,
    "exif": {}
  },
  {
    "id": "dg3kxk4lr",
    "url": "photos/浙江大明山/d6e16fe0f8f28c24c56804388b6d5183.jpg",
    "thumb": "thumbs/浙江大明山/d6e16fe0f8f28c24c56804388b6d5183.jpg",
    "name": "d6e16fe0f8f28c24c56804388b6d5183.jpg",
    "category": "浙江大明山",
    "date": "2025-12-11T12:21:34.912Z",
    "size": "85.32 KB",
    "width": 0,
    "height": 0,
    "exif": {}
  },
  {
    "id": "0nmsum9an",
    "url": "photos/浙江大明山/f8a028cd83f4f1254b4db08eab566f73.jpg",
    "thumb": "thumbs/浙江大明山/f8a028cd83f4f1254b4db08eab566f73.jpg",
    "name": "f8a028cd83f4f1254b4db08eab566f73.jpg",
    "category": "浙江大明山",
    "date": "2025-12-11T12:21:33.551Z",
    "size": "38.05 KB",
    "width": 0,
    "height": 0,
    "exif": {}
  },
  {
    "id": "c2hkfdw9i",
    "url": "photos/浙江大明山/b36adcc294fe31be34e06c160df3912c.jpg",
    "thumb": "thumbs/浙江大明山/b36adcc294fe31be34e06c160df3912c.jpg",
    "name": "b36adcc294fe31be34e06c160df3912c.jpg",
    "category": "浙江大明山",
    "date": "2025-12-11T12:21:32.828Z",
    "size": "82.28 KB",
    "width": 0,
    "height": 0,
    "exif": {}
  },
  {
    "id": "5uplog011",
    "url": "photos/广富林/128aac7c1cc5b76f2a00cf6e700c6007.jpg",
    "thumb": "thumbs/广富林/128aac7c1cc5b76f2a00cf6e700c6007.jpg",
    "name": "128aac7c1cc5b76f2a00cf6e700c6007.jpg",
    "category": "广富林",
    "date": "2025-12-11T12:20:57.188Z",
    "size": "427.98 KB",
    "width": 0,
    "height": 0,
    "exif": {}
  },
  {
    "id": "fwtuv8i8i",
    "url": "photos/广富林/ea67b4112c203670e72dcf1dcd36eb1e.jpg",
    "thumb": "thumbs/广富林/ea67b4112c203670e72dcf1dcd36eb1e.jpg",
    "name": "ea67b4112c203670e72dcf1dcd36eb1e.jpg",
    "category": "广富林",
    "date": "2025-12-11T12:20:41.171Z",
    "size": "544.67 KB",
    "width": 0,
    "height": 0,
    "exif": {}
  },
  {
    "id": "y1vama72g",
    "url": "photos/广富林/39409f8efdce80478e38fdaaffa1f00d.jpg",
    "thumb": "thumbs/广富林/39409f8efdce80478e38fdaaffa1f00d.jpg",
    "name": "39409f8efdce80478e38fdaaffa1f00d.jpg",
    "category": "广富林",
    "date": "2025-12-11T12:20:40.280Z",
    "size": "243.98 KB",
    "width": 0,
    "height": 0,
    "exif": {}
  },
  {
    "id": "mavai80zz",
    "url": "photos/广富林/c857a680c71e4f2875e93d5ba6b4fd98.jpg",
    "thumb": "thumbs/广富林/c857a680c71e4f2875e93d5ba6b4fd98.jpg",
    "name": "c857a680c71e4f2875e93d5ba6b4fd98.jpg",
    "category": "广富林",
    "date": "2025-12-11T12:20:39.440Z",
    "size": "448.07 KB",
    "width": 0,
    "height": 0,
    "exif": {}
  },
  {
    "id": "s9p8m7xej",
    "url": "photos/广富林/9aea11737bf97d6c53f0ef7fca71b5cf.jpg",
    "thumb": "thumbs/广富林/9aea11737bf97d6c53f0ef7fca71b5cf.jpg",
    "name": "9aea11737bf97d6c53f0ef7fca71b5cf.jpg",
    "category": "广富林",
    "date": "2025-12-11T12:20:35.519Z",
    "size": "236.84 KB",
    "width": 0,
    "height": 0,
    "exif": {}
  },
  {
    "id": "3qwkn6v1c",
    "url": "photos/广富林/fa99103ab1dfd630267d3f16bab2bfb6.jpg",
    "thumb": "thumbs/广富林/fa99103ab1dfd630267d3f16bab2bfb6.jpg",
    "name": "fa99103ab1dfd630267d3f16bab2bfb6.jpg",
    "category": "广富林",
    "date": "2025-12-11T12:20:34.228Z",
    "size": "156.07 KB",
    "width": 0,
    "height": 0,
    "exif": {}
  },
  {
    "id": "bvoby5ys8",
    "url": "photos/广富林/d0f991be66a1186fda98a52be363983f.jpg",
    "thumb": "thumbs/广富林/d0f991be66a1186fda98a52be363983f.jpg",
    "name": "d0f991be66a1186fda98a52be363983f.jpg",
    "category": "广富林",
    "date": "2025-12-11T12:20:32.794Z",
    "size": "96.27 KB",
    "width": 0,
    "height": 0,
    "exif": {}
  },
  {
    "id": "o8hpf9a7l",
    "url": "photos/浙江九龙山/16dbaca7fe28143c8c612b85176e26e8.jpg",
    "thumb": "thumbs/浙江九龙山/16dbaca7fe28143c8c612b85176e26e8.jpg",
    "name": "16dbaca7fe28143c8c612b85176e26e8.jpg",
    "category": "浙江九龙山",
    "date": "2025-12-11T12:19:10.481Z",
    "size": "2.6 MB",
    "width": 0,
    "height": 0,
    "exif": {
      "make": "",
      "model": "",
      "software": "-",
      "focal": "35mm",
      "fstop": "f/11",
      "iso": "100",
      "shutter": "1/200",
      "lens": "N\u0000NIKKOR Z 24-70mm f/4",
      "focal35": "34mm",
      "whiteBalance": "Auto",
      "exposureProgram": "Manual",
      "meteringMode": "Pattern",
      "flash": "关闭",
      "brightness": "-",
      "exposureBias": "0 EV",
      "sensingMethod": "One-chip color area sensor",
      "gps": null
    }
  },
  {
    "id": "lqgne75sg",
    "url": "photos/浙江九龙山/50b32f5df6739957f72b9d179c6bccc7.jpg",
    "thumb": "thumbs/浙江九龙山/50b32f5df6739957f72b9d179c6bccc7.jpg",
    "name": "50b32f5df6739957f72b9d179c6bccc7.jpg",
    "category": "浙江九龙山",
    "date": "2025-12-11T12:19:06.841Z",
    "size": "12.2 MB",
    "width": 6000,
    "height": 4000,
    "exif": {
      "make": "",
      "model": "",
      "software": "-",
      "focal": "24mm",
      "fstop": "f/2.8",
      "iso": "100",
      "shutter": "1/2500",
      "lens": "\u0000\u0000LUMIX S 24-60/F2.8",
      "focal35": "24mm",
      "whiteBalance": "Auto",
      "exposureProgram": "Aperture priority",
      "meteringMode": "Pattern",
      "flash": "关闭",
      "brightness": "-",
      "exposureBias": "0 EV",
      "sensingMethod": "One-chip color area sensor",
      "gps": null
    }
  },
  {
    "id": "aplfhadft",
    "url": "photos/浙江九龙山/7e793e135565e2b5ea8bc5f1bc727d51.jpg",
    "thumb": "thumbs/浙江九龙山/7e793e135565e2b5ea8bc5f1bc727d51.jpg",
    "name": "7e793e135565e2b5ea8bc5f1bc727d51.jpg",
    "category": "浙江九龙山",
    "date": "2025-12-11T12:19:03.730Z",
    "size": "12.3 MB",
    "width": 6000,
    "height": 4000,
    "exif": {
      "make": "",
      "model": "",
      "software": "-",
      "focal": "24mm",
      "fstop": "f/2.8",
      "iso": "250",
      "shutter": "1/5000",
      "lens": "\u0000\u0000LUMIX S 24-60/F2.8",
      "focal35": "24mm",
      "whiteBalance": "Auto",
      "exposureProgram": "Aperture priority",
      "meteringMode": "Pattern",
      "flash": "关闭",
      "brightness": "-",
      "exposureBias": "0 EV",
      "sensingMethod": "One-chip color area sensor",
      "gps": null
    }
  },
  {
    "id": "ogyy8qlv5",
    "url": "photos/浙江九龙山/0c16b2d2bee34d4e99917a50d72e98ec.jpg",
    "thumb": "thumbs/浙江九龙山/0c16b2d2bee34d4e99917a50d72e98ec.jpg",
    "name": "0c16b2d2bee34d4e99917a50d72e98ec.jpg",
    "category": "浙江九龙山",
    "date": "2025-12-11T12:19:01.739Z",
    "size": "12.55 MB",
    "width": 6000,
    "height": 4000,
    "exif": {
      "make": "",
      "model": "",
      "software": "-",
      "focal": "24mm",
      "fstop": "f/22",
      "iso": "12800",
      "shutter": "1/60",
      "lens": "\u0000\u0000LUMIX S 24-60/F2.8",
      "focal35": "24mm",
      "whiteBalance": "Auto",
      "exposureProgram": "Aperture priority",
      "meteringMode": "Pattern",
      "flash": "关闭",
      "brightness": "-",
      "exposureBias": "0 EV",
      "sensingMethod": "One-chip color area sensor",
      "gps": null
    }
  },
  {
    "id": "51yjrglk3",
    "url": "photos/浙江九龙山/69a0feabd27dba5ec73d32ca42ee9c1e.jpg",
    "thumb": "thumbs/浙江九龙山/69a0feabd27dba5ec73d32ca42ee9c1e.jpg",
    "name": "69a0feabd27dba5ec73d32ca42ee9c1e.jpg",
    "category": "浙江九龙山",
    "date": "2025-12-11T12:18:57.820Z",
    "size": "12.27 MB",
    "width": 6000,
    "height": 4000,
    "exif": {
      "make": "",
      "model": "",
      "software": "-",
      "focal": "28mm",
      "fstop": "f/4",
      "iso": "100",
      "shutter": "1/800",
      "lens": "\u0000\u0000LUMIX S 24-60/F2.8",
      "focal35": "28mm",
      "whiteBalance": "Auto",
      "exposureProgram": "Aperture priority",
      "meteringMode": "Pattern",
      "flash": "关闭",
      "brightness": "-",
      "exposureBias": "0 EV",
      "sensingMethod": "One-chip color area sensor",
      "gps": null
    }
  },
  {
    "id": "c85om7j8t",
    "url": "photos/浙江九龙山/60747bcb9320f2667a1818623c1b8983.jpg",
    "thumb": "thumbs/浙江九龙山/60747bcb9320f2667a1818623c1b8983.jpg",
    "name": "60747bcb9320f2667a1818623c1b8983.jpg",
    "category": "浙江九龙山",
    "date": "2025-11-15T06:40:43.000Z",
    "size": "7.26 MB",
    "width": 4350,
    "height": 2900,
    "exif": {
      "make": "Panasonic",
      "model": "DC-S5M2",
      "software": "-",
      "focal": "60mm",
      "fstop": "f/2.8",
      "iso": "200",
      "shutter": "1/4000",
      "lens": "LUMIX S 24-60/F2.8",
      "focal35": "60mm",
      "whiteBalance": "-",
      "exposureProgram": "Aperture priority",
      "meteringMode": "Pattern",
      "flash": "关闭",
      "brightness": "-",
      "exposureBias": "0 EV",
      "sensingMethod": "One-chip color area sensor",
      "gps": null
    }
  },
  {
    "id": "xa4ocmhm3",
    "url": "photos/浙江九龙山/46c9cb987318332c2a7925e3bda2cbb6.jpg",
    "thumb": "thumbs/浙江九龙山/46c9cb987318332c2a7925e3bda2cbb6.jpg",
    "name": "46c9cb987318332c2a7925e3bda2cbb6.jpg",
    "category": "浙江九龙山",
    "date": "2025-11-15T04:32:22.000Z",
    "size": "6.96 MB",
    "width": 3996,
    "height": 5993,
    "exif": {
      "make": "Panasonic",
      "model": "DC-S5M2",
      "software": "-",
      "focal": "24mm",
      "fstop": "f/2.8",
      "iso": "250",
      "shutter": "1/6400",
      "lens": "LUMIX S 24-60/F2.8",
      "focal35": "24mm",
      "whiteBalance": "-",
      "exposureProgram": "Aperture priority",
      "meteringMode": "Pattern",
      "flash": "关闭",
      "brightness": "-",
      "exposureBias": "0 EV",
      "sensingMethod": "One-chip color area sensor",
      "gps": null
    }
  },
  {
    "id": "ayqy9zq1s",
    "url": "photos/浙江九龙山/4370d740aefabf994b9f0ea260c703c1.jpg",
    "thumb": "thumbs/浙江九龙山/4370d740aefabf994b9f0ea260c703c1.jpg",
    "name": "4370d740aefabf994b9f0ea260c703c1.jpg",
    "category": "浙江九龙山",
    "date": "2025-11-15T01:42:07.000Z",
    "size": "10.82 MB",
    "width": 6000,
    "height": 4000,
    "exif": {
      "make": "Panasonic",
      "model": "DC-S5M2",
      "software": "-",
      "focal": "24mm",
      "fstop": "f/4.5",
      "iso": "100",
      "shutter": "1/1300",
      "lens": "LUMIX S 24-60/F2.8",
      "focal35": "24mm",
      "whiteBalance": "-",
      "exposureProgram": "Aperture priority",
      "meteringMode": "Pattern",
      "flash": "关闭",
      "brightness": "-",
      "exposureBias": "0 EV",
      "sensingMethod": "One-chip color area sensor",
      "gps": null
    }
  },
  {
    "id": "j14a1f11a",
    "url": "photos/浙江九龙山/d2eed53d8d3b7ab340b974e52d506481.jpg",
    "thumb": "thumbs/浙江九龙山/d2eed53d8d3b7ab340b974e52d506481.jpg",
    "name": "d2eed53d8d3b7ab340b974e52d506481.jpg",
    "category": "浙江九龙山",
    "date": "2025-11-15T00:56:46.000Z",
    "size": "7.92 MB",
    "width": 5938,
    "height": 3958,
    "exif": {
      "make": "Panasonic",
      "model": "DC-S5M2",
      "software": "-",
      "focal": "35mm",
      "fstop": "f/4",
      "iso": "100",
      "shutter": "1/1600",
      "lens": "LUMIX S 24-60/F2.8",
      "focal35": "35mm",
      "whiteBalance": "-",
      "exposureProgram": "Aperture priority",
      "meteringMode": "Pattern",
      "flash": "关闭",
      "brightness": "-",
      "exposureBias": "0 EV",
      "sensingMethod": "One-chip color area sensor",
      "gps": null
    }
  },
  {
    "id": "xrofaxyeq",
    "url": "photos/南京/1728122758605.jpeg",
    "thumb": "thumbs/南京/1728122758605.jpeg",
    "name": "1728122758605.jpeg",
    "category": "南京",
    "date": "2024-11-27T08:12:32.000Z",
    "size": "829.04 KB",
    "width": 3205,
    "height": 1440,
    "exif": {
      "make": "",
      "model": "",
      "software": "-",
      "focal": "-",
      "fstop": "-",
      "iso": "-",
      "shutter": "-",
      "lens": "-",
      "focal35": "-",
      "whiteBalance": "-",
      "exposureProgram": "-",
      "meteringMode": "-",
      "flash": "-",
      "brightness": "-",
      "exposureBias": "0 EV",
      "sensingMethod": "-",
      "gps": null
    }
  },
  {
    "id": "20ugyypg5",
    "url": "photos/南京/1728298904000.jpeg",
    "thumb": "thumbs/南京/1728298904000.jpeg",
    "name": "1728298904000.jpeg",
    "category": "南京",
    "date": "2024-11-27T08:12:30.000Z",
    "size": "499.52 KB",
    "width": 1080,
    "height": 721,
    "exif": {
      "make": "",
      "model": "",
      "software": "Capture One Windows",
      "focal": "-",
      "fstop": "-",
      "iso": "-",
      "shutter": "-",
      "lens": "-",
      "focal35": "-",
      "whiteBalance": "-",
      "exposureProgram": "-",
      "meteringMode": "-",
      "flash": "-",
      "brightness": "-",
      "exposureBias": "0 EV",
      "sensingMethod": "-",
      "gps": null
    }
  },
  {
    "id": "o4ivywr8r",
    "url": "photos/南京/1728298913000.jpeg",
    "thumb": "thumbs/南京/1728298913000.jpeg",
    "name": "1728298913000.jpeg",
    "category": "南京",
    "date": "2024-11-27T08:12:30.000Z",
    "size": "2.32 MB",
    "width": 2048,
    "height": 1366,
    "exif": {
      "make": "",
      "model": "",
      "software": "-",
      "focal": "-",
      "fstop": "-",
      "iso": "-",
      "shutter": "-",
      "lens": "-",
      "focal35": "-",
      "whiteBalance": "-",
      "exposureProgram": "-",
      "meteringMode": "-",
      "flash": "-",
      "brightness": "-",
      "exposureBias": "0 EV",
      "sensingMethod": "-",
      "gps": null
    }
  },
  {
    "id": "q1icozvd4",
    "url": "photos/南京/1728122758425.jpeg",
    "thumb": "thumbs/南京/1728122758425.jpeg",
    "name": "1728122758425.jpeg",
    "category": "南京",
    "date": "2024-11-27T08:12:24.000Z",
    "size": "336.4 KB",
    "width": 700,
    "height": 870,
    "exif": {
      "make": "",
      "model": "",
      "software": "-",
      "focal": "-",
      "fstop": "-",
      "iso": "-",
      "shutter": "-",
      "lens": "-",
      "focal35": "-",
      "whiteBalance": "-",
      "exposureProgram": "-",
      "meteringMode": "-",
      "flash": "-",
      "brightness": "-",
      "exposureBias": "0 EV",
      "sensingMethod": "-",
      "gps": null
    }
  },
  {
    "id": "76fya7ngn",
    "url": "photos/南京/1728123269478.jpeg",
    "thumb": "thumbs/南京/1728123269478.jpeg",
    "name": "1728123269478.jpeg",
    "category": "南京",
    "date": "2024-11-27T08:12:22.000Z",
    "size": "425.77 KB",
    "width": 1440,
    "height": 1920,
    "exif": {
      "make": "",
      "model": "",
      "software": "-",
      "focal": "-",
      "fstop": "-",
      "iso": "-",
      "shutter": "-",
      "lens": "-",
      "focal35": "-",
      "whiteBalance": "-",
      "exposureProgram": "-",
      "meteringMode": "-",
      "flash": "-",
      "brightness": "-",
      "exposureBias": "0 EV",
      "sensingMethod": "-",
      "gps": null
    }
  },
  {
    "id": "6ksdyu9zo",
    "url": "photos/南京/1728298916000.jpeg",
    "thumb": "thumbs/南京/1728298916000.jpeg",
    "name": "1728298916000.jpeg",
    "category": "南京",
    "date": "2024-11-27T08:12:12.000Z",
    "size": "625.28 KB",
    "width": 1366,
    "height": 2048,
    "exif": {
      "make": "",
      "model": "",
      "software": "-",
      "focal": "-",
      "fstop": "-",
      "iso": "-",
      "shutter": "-",
      "lens": "-",
      "focal35": "-",
      "whiteBalance": "-",
      "exposureProgram": "-",
      "meteringMode": "-",
      "flash": "-",
      "brightness": "-",
      "exposureBias": "0 EV",
      "sensingMethod": "-",
      "gps": null
    }
  },
  {
    "id": "rxnc8x67x",
    "url": "photos/南京/1728122349114.jpeg",
    "thumb": "thumbs/南京/1728122349114.jpeg",
    "name": "1728122349114.jpeg",
    "category": "南京",
    "date": "2024-11-27T08:12:08.000Z",
    "size": "318.59 KB",
    "width": 700,
    "height": 933,
    "exif": {
      "make": "",
      "model": "",
      "software": "-",
      "focal": "-",
      "fstop": "-",
      "iso": "-",
      "shutter": "-",
      "lens": "-",
      "focal35": "-",
      "whiteBalance": "-",
      "exposureProgram": "-",
      "meteringMode": "-",
      "flash": "-",
      "brightness": "-",
      "exposureBias": "0 EV",
      "sensingMethod": "-",
      "gps": null
    }
  },
  {
    "id": "q1jtqxbw1",
    "url": "photos/南京/1728298906000.jpeg",
    "thumb": "thumbs/南京/1728298906000.jpeg",
    "name": "1728298906000.jpeg",
    "category": "南京",
    "date": "2024-11-27T08:11:40.000Z",
    "size": "428.06 KB",
    "width": 1080,
    "height": 1619,
    "exif": {
      "make": "",
      "model": "",
      "software": "Snapseed 2.25.642066665",
      "focal": "-",
      "fstop": "-",
      "iso": "-",
      "shutter": "-",
      "lens": "-",
      "focal35": "-",
      "whiteBalance": "-",
      "exposureProgram": "-",
      "meteringMode": "-",
      "flash": "-",
      "brightness": "-",
      "exposureBias": "0 EV",
      "sensingMethod": "-",
      "gps": null
    }
  },
  {
    "id": "be1sy5pui",
    "url": "photos/南京/1728298918000.jpeg",
    "thumb": "thumbs/南京/1728298918000.jpeg",
    "name": "1728298918000.jpeg",
    "category": "南京",
    "date": "2024-11-27T08:11:32.000Z",
    "size": "2.04 MB",
    "width": 2048,
    "height": 1366,
    "exif": {
      "make": "",
      "model": "",
      "software": "-",
      "focal": "-",
      "fstop": "-",
      "iso": "-",
      "shutter": "-",
      "lens": "-",
      "focal35": "-",
      "whiteBalance": "-",
      "exposureProgram": "-",
      "meteringMode": "-",
      "flash": "-",
      "brightness": "-",
      "exposureBias": "0 EV",
      "sensingMethod": "-",
      "gps": null
    }
  },
  {
    "id": "yaf5ttyp3",
    "url": "photos/南京/1727945573336.jpeg",
    "thumb": "thumbs/南京/1727945573336.jpeg",
    "name": "1727945573336.jpeg",
    "category": "南京",
    "date": "2024-11-27T08:11:14.000Z",
    "size": "516.06 KB",
    "width": 1440,
    "height": 2158,
    "exif": {
      "make": "",
      "model": "",
      "software": "-",
      "focal": "-",
      "fstop": "-",
      "iso": "-",
      "shutter": "-",
      "lens": "-",
      "focal35": "-",
      "whiteBalance": "-",
      "exposureProgram": "-",
      "meteringMode": "-",
      "flash": "-",
      "brightness": "-",
      "exposureBias": "0 EV",
      "sensingMethod": "-",
      "gps": null
    }
  },
  {
    "id": "b8th52629",
    "url": "photos/南京/1728122758686.jpeg",
    "thumb": "thumbs/南京/1728122758686.jpeg",
    "name": "1728122758686.jpeg",
    "category": "南京",
    "date": "2024-11-27T08:11:14.000Z",
    "size": "482.6 KB",
    "width": 2167,
    "height": 1088,
    "exif": {
      "make": "",
      "model": "",
      "software": "-",
      "focal": "-",
      "fstop": "-",
      "iso": "-",
      "shutter": "-",
      "lens": "-",
      "focal35": "-",
      "whiteBalance": "-",
      "exposureProgram": "-",
      "meteringMode": "-",
      "flash": "-",
      "brightness": "-",
      "exposureBias": "0 EV",
      "sensingMethod": "-",
      "gps": null
    }
  },
  {
    "id": "hfynrg9ys",
    "url": "photos/南京/IMG_3672.JPG.jpeg",
    "thumb": "thumbs/南京/IMG_3672.JPG.jpeg",
    "name": "IMG_3672.JPG.jpeg",
    "category": "南京",
    "date": "2024-10-03T10:05:57.000Z",
    "size": "627.94 KB",
    "width": 4032,
    "height": 3024,
    "exif": {
      "make": "Apple",
      "model": "iPhone 14",
      "software": "18.0",
      "focal": "6mm",
      "fstop": "f/1.5",
      "iso": "50",
      "shutter": "1/2252",
      "lens": "iPhone 14 back dual wide camera 5.7mm f/1.5",
      "focal35": "26mm",
      "whiteBalance": "Auto",
      "exposureProgram": "Normal program",
      "meteringMode": "Pattern",
      "flash": "关闭",
      "brightness": "6.82",
      "exposureBias": "0 EV",
      "sensingMethod": "One-chip color area sensor",
      "gps": {
        "lat": 32.06392777777778,
        "lng": 118.79484444444444
      }
    }
  },
  {
    "id": "7dow959aj",
    "url": "photos/南京/IMG_3650.JPG.jpeg",
    "thumb": "thumbs/南京/IMG_3650.JPG.jpeg",
    "name": "IMG_3650.JPG.jpeg",
    "category": "南京",
    "date": "2024-10-03T09:13:51.000Z",
    "size": "1.46 MB",
    "width": 4032,
    "height": 3024,
    "exif": {
      "make": "Apple",
      "model": "iPhone 14",
      "software": "18.0",
      "focal": "6mm",
      "fstop": "f/1.5",
      "iso": "50",
      "shutter": "1/814",
      "lens": "iPhone 14 back dual wide camera 5.7mm f/1.5",
      "focal35": "26mm",
      "whiteBalance": "Auto",
      "exposureProgram": "Normal program",
      "meteringMode": "Pattern",
      "flash": "关闭",
      "brightness": "5.94",
      "exposureBias": "0 EV",
      "sensingMethod": "One-chip color area sensor",
      "gps": {
        "lat": 32.064055555555555,
        "lng": 118.7903361111111
      }
    }
  },
  {
    "id": "1c91mgerp",
    "url": "photos/南京/IMG_3641.JPG.jpeg",
    "thumb": "thumbs/南京/IMG_3641.JPG.jpeg",
    "name": "IMG_3641.JPG.jpeg",
    "category": "南京",
    "date": "2024-10-03T08:59:13.000Z",
    "size": "1.61 MB",
    "width": 4032,
    "height": 3024,
    "exif": {
      "make": "Apple",
      "model": "iPhone 14",
      "software": "18.0",
      "focal": "6mm",
      "fstop": "f/1.5",
      "iso": "50",
      "shutter": "1/5882",
      "lens": "iPhone 14 back dual wide camera 5.7mm f/1.5",
      "focal35": "31mm",
      "whiteBalance": "Auto",
      "exposureProgram": "Normal program",
      "meteringMode": "Spot",
      "flash": "关闭",
      "brightness": "9.40",
      "exposureBias": "0 EV",
      "sensingMethod": "One-chip color area sensor",
      "gps": {
        "lat": 32.06486388888889,
        "lng": 118.79123055555556
      }
    }
  },
  {
    "id": "ix4fz6gnp",
    "url": "photos/青甘大环线/1725753836830.jpeg",
    "thumb": "thumbs/青甘大环线/1725753836830.jpeg",
    "name": "1725753836830.jpeg",
    "category": "青甘大环线",
    "date": "2024-09-13T02:51:00.000Z",
    "size": "301.57 KB",
    "width": 866,
    "height": 1369,
    "exif": {
      "make": "",
      "model": "",
      "software": "-",
      "focal": "-",
      "fstop": "-",
      "iso": "-",
      "shutter": "-",
      "lens": "-",
      "focal35": "-",
      "whiteBalance": "-",
      "exposureProgram": "-",
      "meteringMode": "-",
      "flash": "-",
      "brightness": "-",
      "exposureBias": "0 EV",
      "sensingMethod": "-",
      "gps": null
    }
  },
  {
    "id": "mulpaqhib",
    "url": "photos/青甘大环线/1725267971000.jpeg",
    "thumb": "thumbs/青甘大环线/1725267971000.jpeg",
    "name": "1725267971000.jpeg",
    "category": "青甘大环线",
    "date": "2024-09-13T02:45:14.000Z",
    "size": "2.31 MB",
    "width": 3021,
    "height": 3740,
    "exif": {
      "make": "",
      "model": "",
      "software": "Snapseed 2.22.412829873",
      "focal": "-",
      "fstop": "-",
      "iso": "-",
      "shutter": "-",
      "lens": "-",
      "focal35": "-",
      "whiteBalance": "-",
      "exposureProgram": "-",
      "meteringMode": "-",
      "flash": "-",
      "brightness": "-",
      "exposureBias": "0 EV",
      "sensingMethod": "-",
      "gps": null
    }
  },
  {
    "id": "dd6fikgpp",
    "url": "photos/青甘大环线/1725859718657.jpeg",
    "thumb": "thumbs/青甘大环线/1725859718657.jpeg",
    "name": "1725859718657.jpeg",
    "category": "青甘大环线",
    "date": "2024-09-09T05:28:38.000Z",
    "size": "652.57 KB",
    "width": 2412,
    "height": 1356,
    "exif": {
      "make": "Apple",
      "model": "iPhone 14",
      "software": "17.6.1",
      "focal": "2mm",
      "fstop": "f/2.4",
      "iso": "125",
      "shutter": "1/598",
      "lens": "iPhone 14 back camera 1.54mm f/2.4",
      "focal35": "25mm",
      "whiteBalance": "Auto",
      "exposureProgram": "Normal program",
      "meteringMode": "Pattern",
      "flash": "关闭",
      "brightness": "8.53",
      "exposureBias": "0 EV",
      "sensingMethod": "One-chip color area sensor",
      "gps": {
        "lat": 36.86398888888889,
        "lng": 99.68218888888889
      }
    }
  },
  {
    "id": "ttz4xw9g1",
    "url": "photos/青甘大环线/IMG_3357.JPG.jpeg",
    "thumb": "thumbs/青甘大环线/IMG_3357.JPG.jpeg",
    "name": "IMG_3357.JPG.jpeg",
    "category": "青甘大环线",
    "date": "2024-09-09T04:20:45.000Z",
    "size": "921.43 KB",
    "width": 4032,
    "height": 3024,
    "exif": {
      "make": "Apple",
      "model": "iPhone 14",
      "software": "17.6.1",
      "focal": "6mm",
      "fstop": "f/1.5",
      "iso": "50",
      "shutter": "1/16393",
      "lens": "iPhone 14 back dual wide camera 5.7mm f/1.5",
      "focal35": "63mm",
      "whiteBalance": "Auto",
      "exposureProgram": "Normal program",
      "meteringMode": "Spot",
      "flash": "关闭",
      "brightness": "10.60",
      "exposureBias": "0 EV",
      "sensingMethod": "One-chip color area sensor",
      "gps": {
        "lat": 36.69603333333333,
        "lng": 99.45953333333334
      }
    }
  },
  {
    "id": "pqe3mbod6",
    "url": "photos/青甘大环线/FullSizeRender.heic.heic",
    "thumb": "thumbs/青甘大环线/FullSizeRender.heic.heic",
    "name": "FullSizeRender.heic.heic",
    "category": "青甘大环线",
    "date": "2024-09-08T03:11:55.000Z",
    "size": "960.01 KB",
    "width": 4032,
    "height": 3024,
    "exif": {
      "make": "Apple",
      "model": "iPhone 14 Pro Max",
      "software": "16.1.2",
      "focal": "7mm",
      "fstop": "f/1.78",
      "iso": "64",
      "shutter": "1/12048",
      "lens": "iPhone 14 Pro Max back triple camera 6.86mm f/1.78",
      "focal35": "51mm",
      "whiteBalance": "Auto",
      "exposureProgram": "Normal program",
      "meteringMode": "Pattern",
      "flash": "关闭",
      "brightness": "11.56",
      "exposureBias": "0 EV",
      "sensingMethod": "One-chip color area sensor",
      "gps": {
        "lat": 36.86055277777778,
        "lng": 95.27284166666666
      }
    }
  },
  {
    "id": "17c0qfakq",
    "url": "photos/青甘大环线/1725681272218.jpeg",
    "thumb": "thumbs/青甘大环线/1725681272218.jpeg",
    "name": "1725681272218.jpeg",
    "category": "青甘大环线",
    "date": "2024-09-07T03:54:32.000Z",
    "size": "1.02 MB",
    "width": 2412,
    "height": 1356,
    "exif": {
      "make": "Apple",
      "model": "iPhone 14",
      "software": "17.6.1",
      "focal": "2mm",
      "fstop": "f/2.4",
      "iso": "64",
      "shutter": "1/737",
      "lens": "iPhone 14 back camera 1.54mm f/2.4",
      "focal35": "25mm",
      "whiteBalance": "Auto",
      "exposureProgram": "Normal program",
      "meteringMode": "Spot",
      "flash": "关闭",
      "brightness": "9.75",
      "exposureBias": "0 EV",
      "sensingMethod": "One-chip color area sensor",
      "gps": {
        "lat": 35.640702777777776,
        "lng": 94.06816944444444
      }
    }
  },
  {
    "id": "lud1zaeyw",
    "url": "photos/青甘大环线/IMG_3163.JPG.jpeg",
    "thumb": "thumbs/青甘大环线/IMG_3163.JPG.jpeg",
    "name": "IMG_3163.JPG.jpeg",
    "category": "青甘大环线",
    "date": "2024-09-07T02:19:47.000Z",
    "size": "580.4 KB",
    "width": 4032,
    "height": 3024,
    "exif": {
      "make": "Apple",
      "model": "iPhone 14",
      "software": "17.6.1",
      "focal": "6mm",
      "fstop": "f/1.5",
      "iso": "50",
      "shutter": "1/12658",
      "lens": "iPhone 14 back dual wide camera 5.7mm f/1.5",
      "focal35": "48mm",
      "whiteBalance": "Auto",
      "exposureProgram": "Normal program",
      "meteringMode": "Spot",
      "flash": "关闭",
      "brightness": "10.21",
      "exposureBias": "0 EV",
      "sensingMethod": "One-chip color area sensor",
      "gps": {
        "lat": 35.79473888888889,
        "lng": 94.34029444444444
      }
    }
  },
  {
    "id": "9ceh60bht",
    "url": "photos/青甘大环线/1725646519000.jpeg",
    "thumb": "thumbs/青甘大环线/1725646519000.jpeg",
    "name": "1725646519000.jpeg",
    "category": "青甘大环线",
    "date": "2024-09-06T18:15:19.000Z",
    "size": "437.07 KB",
    "width": 1920,
    "height": 1080,
    "exif": {
      "make": "SONY",
      "model": "ILCE-7RM2",
      "software": "ILCE-7RM2 v3.30",
      "focal": "50mm",
      "fstop": "f/18",
      "iso": "50",
      "shutter": "1/60",
      "lens": "YN50mm f/1.8S DF DSM",
      "focal35": "75mm",
      "whiteBalance": "Manual",
      "exposureProgram": "Aperture priority",
      "meteringMode": "Pattern",
      "flash": "关闭",
      "brightness": "10.86",
      "exposureBias": "0 EV",
      "sensingMethod": "-",
      "gps": null
    }
  },
  {
    "id": "qyj31dizb",
    "url": "photos/青甘大环线/1725646158000.jpeg",
    "thumb": "thumbs/青甘大环线/1725646158000.jpeg",
    "name": "1725646158000.jpeg",
    "category": "青甘大环线",
    "date": "2024-09-06T18:09:18.000Z",
    "size": "379.83 KB",
    "width": 1920,
    "height": 1080,
    "exif": {
      "make": "SONY",
      "model": "ILCE-7RM2",
      "software": "ILCE-7RM2 v3.30",
      "focal": "50mm",
      "fstop": "f/11",
      "iso": "50",
      "shutter": "1/80",
      "lens": "YN50mm f/1.8S DF DSM",
      "focal35": "75mm",
      "whiteBalance": "Manual",
      "exposureProgram": "Aperture priority",
      "meteringMode": "Pattern",
      "flash": "关闭",
      "brightness": "10.38",
      "exposureBias": "0 EV",
      "sensingMethod": "-",
      "gps": null
    }
  },
  {
    "id": "st6208l9q",
    "url": "photos/青甘大环线/1725640922000_1726195734413_37.jpeg",
    "thumb": "thumbs/青甘大环线/1725640922000_1726195734413_37.jpeg",
    "name": "1725640922000_1726195734413_37.jpeg",
    "category": "青甘大环线",
    "date": "2024-09-06T16:42:02.000Z",
    "size": "1.2 MB",
    "width": 1920,
    "height": 1080,
    "exif": {
      "make": "SONY",
      "model": "ILCE-7RM2",
      "software": "ILCE-7RM2 v3.30",
      "focal": "50mm",
      "fstop": "f/2.2",
      "iso": "100",
      "shutter": "1/5000",
      "lens": "YN50mm f/1.8S DF DSM",
      "focal35": "75mm",
      "whiteBalance": "Manual",
      "exposureProgram": "Aperture priority",
      "meteringMode": "Pattern",
      "flash": "关闭",
      "brightness": "10.75",
      "exposureBias": "0 EV",
      "sensingMethod": "-",
      "gps": null
    }
  },
  {
    "id": "m05o4hdao",
    "url": "photos/青甘大环线/1725640355000.jpeg",
    "thumb": "thumbs/青甘大环线/1725640355000.jpeg",
    "name": "1725640355000.jpeg",
    "category": "青甘大环线",
    "date": "2024-09-06T16:32:35.000Z",
    "size": "409.77 KB",
    "width": 1920,
    "height": 1080,
    "exif": {
      "make": "SONY",
      "model": "ILCE-7RM2",
      "software": "ILCE-7RM2 v3.30",
      "focal": "50mm",
      "fstop": "f/6.3",
      "iso": "50",
      "shutter": "1/320",
      "lens": "YN50mm f/1.8S DF DSM",
      "focal35": "75mm",
      "whiteBalance": "Manual",
      "exposureProgram": "Aperture priority",
      "meteringMode": "Pattern",
      "flash": "关闭",
      "brightness": "9.37",
      "exposureBias": "0 EV",
      "sensingMethod": "-",
      "gps": null
    }
  },
  {
    "id": "xdids4kyg",
    "url": "photos/青甘大环线/1725565580000.jpeg",
    "thumb": "thumbs/青甘大环线/1725565580000.jpeg",
    "name": "1725565580000.jpeg",
    "category": "青甘大环线",
    "date": "2024-09-05T19:46:20.000Z",
    "size": "719.18 KB",
    "width": 1920,
    "height": 1080,
    "exif": {
      "make": "SONY",
      "model": "ILCE-7RM2",
      "software": "ILCE-7RM2 v3.30",
      "focal": "50mm",
      "fstop": "f/2",
      "iso": "50",
      "shutter": "1/4000",
      "lens": "YN50mm f/1.8S DF DSM",
      "focal35": "75mm",
      "whiteBalance": "Manual",
      "exposureProgram": "Manual",
      "meteringMode": "Pattern",
      "flash": "关闭",
      "brightness": "10.25",
      "exposureBias": "0 EV",
      "sensingMethod": "-",
      "gps": null
    }
  },
  {
    "id": "gubqc1eot",
    "url": "photos/青甘大环线/1725563625000.jpeg",
    "thumb": "thumbs/青甘大环线/1725563625000.jpeg",
    "name": "1725563625000.jpeg",
    "category": "青甘大环线",
    "date": "2024-09-05T19:13:45.000Z",
    "size": "1019.2 KB",
    "width": 1920,
    "height": 1080,
    "exif": {
      "make": "SONY",
      "model": "ILCE-7RM2",
      "software": "ILCE-7RM2 v3.30",
      "focal": "50mm",
      "fstop": "f/3.5",
      "iso": "50",
      "shutter": "1/2000",
      "lens": "YN50mm f/1.8S DF DSM",
      "focal35": "75mm",
      "whiteBalance": "Auto",
      "exposureProgram": "Manual",
      "meteringMode": "Pattern",
      "flash": "关闭",
      "brightness": "10.79",
      "exposureBias": "0 EV",
      "sensingMethod": "-",
      "gps": null
    }
  },
  {
    "id": "5v677wjau",
    "url": "photos/青甘大环线/IMG_3026.JPG.jpeg",
    "thumb": "thumbs/青甘大环线/IMG_3026.JPG.jpeg",
    "name": "IMG_3026.JPG.jpeg",
    "category": "青甘大环线",
    "date": "2024-09-05T11:47:27.000Z",
    "size": "1.23 MB",
    "width": 4032,
    "height": 3024,
    "exif": {
      "make": "Apple",
      "model": "iPhone 14",
      "software": "17.6.1",
      "focal": "6mm",
      "fstop": "f/1.5",
      "iso": "40",
      "shutter": "1/19231",
      "lens": "iPhone 14 back dual wide camera 5.7mm f/1.5",
      "focal35": "26mm",
      "whiteBalance": "Auto",
      "exposureProgram": "Normal program",
      "meteringMode": "Pattern",
      "flash": "关闭",
      "brightness": "10.97",
      "exposureBias": "0 EV",
      "sensingMethod": "One-chip color area sensor",
      "gps": {
        "lat": 39.62235277777778,
        "lng": 94.33521944444443
      }
    }
  },
  {
    "id": "1torgxvaw",
    "url": "photos/青甘大环线/IMG_8004.HEIC.heic",
    "thumb": "thumbs/青甘大环线/IMG_8004.HEIC.heic",
    "name": "IMG_8004.HEIC.heic",
    "category": "青甘大环线",
    "date": "2024-09-04T12:15:40.000Z",
    "size": "1.26 MB",
    "width": 4032,
    "height": 3024,
    "exif": {
      "make": "Apple",
      "model": "iPhone 14 Pro Max",
      "software": "16.1.2",
      "focal": "7mm",
      "fstop": "f/1.78",
      "iso": "125",
      "shutter": "1/121",
      "lens": "iPhone 14 Pro Max back triple camera 6.86mm f/1.78",
      "focal35": "26mm",
      "whiteBalance": "Auto",
      "exposureProgram": "Normal program",
      "meteringMode": "Pattern",
      "flash": "关闭",
      "brightness": "3.89",
      "exposureBias": "0 EV",
      "sensingMethod": "One-chip color area sensor",
      "gps": {
        "lat": 40.08428611111111,
        "lng": 94.67565833333333
      }
    }
  },
  {
    "id": "3pm6qq17s",
    "url": "photos/青甘大环线/IMG_2834.JPG.jpeg",
    "thumb": "thumbs/青甘大环线/IMG_2834.JPG.jpeg",
    "name": "IMG_2834.JPG.jpeg",
    "category": "青甘大环线",
    "date": "2024-09-04T11:02:45.000Z",
    "size": "1.24 MB",
    "width": 4032,
    "height": 3024,
    "exif": {
      "make": "Apple",
      "model": "iPhone 14",
      "software": "17.6.1",
      "focal": "6mm",
      "fstop": "f/1.5",
      "iso": "50",
      "shutter": "1/4115",
      "lens": "iPhone 14 back dual wide camera 5.7mm f/1.5",
      "focal35": "26mm",
      "whiteBalance": "Auto",
      "exposureProgram": "Normal program",
      "meteringMode": "Pattern",
      "flash": "关闭",
      "brightness": "10.07",
      "exposureBias": "0 EV",
      "sensingMethod": "One-chip color area sensor",
      "gps": {
        "lat": 40.08646666666667,
        "lng": 94.68416666666667
      }
    }
  },
  {
    "id": "w3qirziyh",
    "url": "photos/青甘大环线/1725446568517.jpeg",
    "thumb": "thumbs/青甘大环线/1725446568517.jpeg",
    "name": "1725446568517.jpeg",
    "category": "青甘大环线",
    "date": "2024-09-04T10:42:48.000Z",
    "size": "1.83 MB",
    "width": 3088,
    "height": 2316,
    "exif": {
      "make": "Apple",
      "model": "iPhone 14",
      "software": "17.6.1",
      "focal": "3mm",
      "fstop": "f/1.9",
      "iso": "25",
      "shutter": "1/363",
      "lens": "iPhone 14 front TrueDepth camera 2.69mm f/1.9",
      "focal35": "30mm",
      "whiteBalance": "Auto",
      "exposureProgram": "Normal program",
      "meteringMode": "Pattern",
      "flash": "关闭",
      "brightness": "8.08",
      "exposureBias": "0 EV",
      "sensingMethod": "One-chip color area sensor",
      "gps": {
        "lat": 40.08906944444445,
        "lng": 94.67974722222223
      }
    }
  },
  {
    "id": "ip81crrg4",
    "url": "photos/青甘大环线/IMG_2811.JPG.jpeg",
    "thumb": "thumbs/青甘大环线/IMG_2811.JPG.jpeg",
    "name": "IMG_2811.JPG.jpeg",
    "category": "青甘大环线",
    "date": "2024-09-04T05:19:49.000Z",
    "size": "2.46 MB",
    "width": 4032,
    "height": 3024,
    "exif": {
      "make": "Apple",
      "model": "iPhone 14",
      "software": "17.6.1",
      "focal": "2mm",
      "fstop": "f/2.4",
      "iso": "32",
      "shutter": "1/2179",
      "lens": "iPhone 14 back dual wide camera 1.54mm f/2.4",
      "focal35": "14mm",
      "whiteBalance": "Auto",
      "exposureProgram": "Normal program",
      "meteringMode": "Pattern",
      "flash": "关闭",
      "brightness": "10.48",
      "exposureBias": "0 EV",
      "sensingMethod": "One-chip color area sensor",
      "gps": {
        "lat": 40.03715555555555,
        "lng": 94.80606944444445
      }
    }
  },
  {
    "id": "tpuw0lltp",
    "url": "photos/青甘大环线/1725420026600.heic",
    "thumb": "thumbs/青甘大环线/1725420026600.heic",
    "name": "1725420026600.heic",
    "category": "青甘大环线",
    "date": "2024-09-04T03:20:26.000Z",
    "size": "953.99 KB",
    "width": 4032,
    "height": 3024,
    "exif": {
      "make": "Apple",
      "model": "iPhone 14 Pro Max",
      "software": "17.6.1",
      "focal": "7mm",
      "fstop": "f/1.78",
      "iso": "80",
      "shutter": "1/7042",
      "lens": "iPhone 14 Pro Max back triple camera 6.86mm f/1.78",
      "focal35": "30mm",
      "whiteBalance": "Auto",
      "exposureProgram": "Normal program",
      "meteringMode": "Pattern",
      "flash": "关闭",
      "brightness": "10.39",
      "exposureBias": "0 EV",
      "sensingMethod": "One-chip color area sensor",
      "gps": {
        "lat": 40.160174999999995,
        "lng": 94.76698333333333
      }
    }
  },
  {
    "id": "73dj4vjpo",
    "url": "photos/青甘大环线/1725409295000_1726195133718_19.jpeg",
    "thumb": "thumbs/青甘大环线/1725409295000_1726195133718_19.jpeg",
    "name": "1725409295000_1726195133718_19.jpeg",
    "category": "青甘大环线",
    "date": "2024-09-04T00:21:35.000Z",
    "size": "413.37 KB",
    "width": 1920,
    "height": 1080,
    "exif": {
      "make": "SONY",
      "model": "ILCE-7RM2",
      "software": "ILCE-7RM2 v3.30",
      "focal": "50mm",
      "fstop": "f/3.5",
      "iso": "100",
      "shutter": "1/250",
      "lens": "YN50mm f/1.8S DF DSM",
      "focal35": "50mm",
      "whiteBalance": "Auto",
      "exposureProgram": "Manual",
      "meteringMode": "Pattern",
      "flash": "关闭",
      "brightness": "4.98",
      "exposureBias": "0 EV",
      "sensingMethod": "-",
      "gps": null
    }
  },
  {
    "id": "8sy912gg7",
    "url": "photos/青甘大环线/1725408696000.jpeg",
    "thumb": "thumbs/青甘大环线/1725408696000.jpeg",
    "name": "1725408696000.jpeg",
    "category": "青甘大环线",
    "date": "2024-09-04T00:11:36.000Z",
    "size": "422.71 KB",
    "width": 1920,
    "height": 1080,
    "exif": {
      "make": "SONY",
      "model": "ILCE-7RM2",
      "software": "ILCE-7RM2 v3.30",
      "focal": "50mm",
      "fstop": "f/1.8",
      "iso": "50",
      "shutter": "1/80",
      "lens": "YN50mm f/1.8S DF DSM",
      "focal35": "50mm",
      "whiteBalance": "Auto",
      "exposureProgram": "Manual",
      "meteringMode": "Pattern",
      "flash": "关闭",
      "brightness": "4.54",
      "exposureBias": "0 EV",
      "sensingMethod": "-",
      "gps": null
    }
  },
  {
    "id": "7gvsj3pde",
    "url": "photos/青甘大环线/1725401003000.jpeg",
    "thumb": "thumbs/青甘大环线/1725401003000.jpeg",
    "name": "1725401003000.jpeg",
    "category": "青甘大环线",
    "date": "2024-09-03T22:03:23.000Z",
    "size": "463.17 KB",
    "width": 1920,
    "height": 1080,
    "exif": {
      "make": "SONY",
      "model": "ILCE-7RM2",
      "software": "ILCE-7RM2 v3.30",
      "focal": "50mm",
      "fstop": "f/1.8",
      "iso": "50",
      "shutter": "1/2500",
      "lens": "YN50mm f/1.8S DF DSM",
      "focal35": "75mm",
      "whiteBalance": "Auto",
      "exposureProgram": "Manual",
      "meteringMode": "Pattern",
      "flash": "关闭",
      "brightness": "10.36",
      "exposureBias": "0 EV",
      "sensingMethod": "-",
      "gps": null
    }
  },
  {
    "id": "xbi8pdil6",
    "url": "photos/青甘大环线/1725209555000_1726195314790_53.jpeg",
    "thumb": "thumbs/青甘大环线/1725209555000_1726195314790_53.jpeg",
    "name": "1725209555000_1726195314790_53.jpeg",
    "category": "青甘大环线",
    "date": "2024-09-01T16:52:35.000Z",
    "size": "7.25 MB",
    "width": 5168,
    "height": 2912,
    "exif": {
      "make": "SONY",
      "model": "ILCE-7RM2",
      "software": "ILCE-7RM2 v3.30",
      "focal": "50mm",
      "fstop": "f/1.8",
      "iso": "100",
      "shutter": "1/3200",
      "lens": "YN50mm f/1.8S DF DSM",
      "focal35": "75mm",
      "whiteBalance": "Auto",
      "exposureProgram": "Aperture priority",
      "meteringMode": "Pattern",
      "flash": "关闭",
      "brightness": "9.33",
      "exposureBias": "0 EV",
      "sensingMethod": "-",
      "gps": null
    }
  },
  {
    "id": "6mbkj83vm",
    "url": "photos/青甘大环线/1725208492000.jpeg",
    "thumb": "thumbs/青甘大环线/1725208492000.jpeg",
    "name": "1725208492000.jpeg",
    "category": "青甘大环线",
    "date": "2024-09-01T16:34:52.000Z",
    "size": "15.09 MB",
    "width": 7952,
    "height": 4472,
    "exif": {
      "make": "SONY",
      "model": "ILCE-7RM2",
      "software": "ILCE-7RM2 v3.30",
      "focal": "50mm",
      "fstop": "f/1.8",
      "iso": "100",
      "shutter": "1/5000",
      "lens": "YN50mm f/1.8S DF DSM",
      "focal35": "50mm",
      "whiteBalance": "Auto",
      "exposureProgram": "Aperture priority",
      "meteringMode": "Pattern",
      "flash": "关闭",
      "brightness": "10.24",
      "exposureBias": "0 EV",
      "sensingMethod": "-",
      "gps": null
    }
  },
  {
    "id": "08ubgrbs7",
    "url": "photos/青甘大环线/1725203029000.jpeg",
    "thumb": "thumbs/青甘大环线/1725203029000.jpeg",
    "name": "1725203029000.jpeg",
    "category": "青甘大环线",
    "date": "2024-09-01T15:03:49.000Z",
    "size": "15.66 MB",
    "width": 7952,
    "height": 4472,
    "exif": {
      "make": "SONY",
      "model": "ILCE-7RM2",
      "software": "ILCE-7RM2 v3.30",
      "focal": "50mm",
      "fstop": "f/3.2",
      "iso": "100",
      "shutter": "1/1000",
      "lens": "YN50mm f/1.8S DF DSM",
      "focal35": "50mm",
      "whiteBalance": "Auto",
      "exposureProgram": "Aperture priority",
      "meteringMode": "Pattern",
      "flash": "关闭",
      "brightness": "9.10",
      "exposureBias": "0 EV",
      "sensingMethod": "-",
      "gps": null
    }
  },
  {
    "id": "yap32hf1b",
    "url": "photos/青甘大环线/1725202133000.jpeg",
    "thumb": "thumbs/青甘大环线/1725202133000.jpeg",
    "name": "1725202133000.jpeg",
    "category": "青甘大环线",
    "date": "2024-09-01T14:48:53.000Z",
    "size": "9.38 MB",
    "width": 7952,
    "height": 4472,
    "exif": {
      "make": "SONY",
      "model": "ILCE-7RM2",
      "software": "ILCE-7RM2 v3.30",
      "focal": "50mm",
      "fstop": "f/2.8",
      "iso": "100",
      "shutter": "1/1600",
      "lens": "YN50mm f/1.8S DF DSM",
      "focal35": "50mm",
      "whiteBalance": "Auto",
      "exposureProgram": "Aperture priority",
      "meteringMode": "Pattern",
      "flash": "关闭",
      "brightness": "9.79",
      "exposureBias": "0 EV",
      "sensingMethod": "-",
      "gps": null
    }
  },
  {
    "id": "9w3ue1n36",
    "url": "photos/青甘大环线/1725201432000.jpeg",
    "thumb": "thumbs/青甘大环线/1725201432000.jpeg",
    "name": "1725201432000.jpeg",
    "category": "青甘大环线",
    "date": "2024-09-01T14:37:12.000Z",
    "size": "13.19 MB",
    "width": 7952,
    "height": 4472,
    "exif": {
      "make": "SONY",
      "model": "ILCE-7RM2",
      "software": "ILCE-7RM2 v3.30",
      "focal": "50mm",
      "fstop": "f/1.8",
      "iso": "100",
      "shutter": "1/2500",
      "lens": "YN50mm f/1.8S DF DSM",
      "focal35": "50mm",
      "whiteBalance": "Auto",
      "exposureProgram": "Aperture priority",
      "meteringMode": "Pattern",
      "flash": "关闭",
      "brightness": "8.90",
      "exposureBias": "0 EV",
      "sensingMethod": "-",
      "gps": null
    }
  },
  {
    "id": "u7xf26aon",
    "url": "photos/青甘大环线/1725195560000.jpeg",
    "thumb": "thumbs/青甘大环线/1725195560000.jpeg",
    "name": "1725195560000.jpeg",
    "category": "青甘大环线",
    "date": "2024-09-01T12:59:20.000Z",
    "size": "2.91 MB",
    "width": 7952,
    "height": 4472,
    "exif": {
      "make": "SONY",
      "model": "ILCE-7RM2",
      "software": "ILCE-7RM2 v3.30",
      "focal": "50mm",
      "fstop": "f/1.8",
      "iso": "50",
      "shutter": "1/13",
      "lens": "YN50mm f/1.8S DF DSM",
      "focal35": "50mm",
      "whiteBalance": "Auto",
      "exposureProgram": "Manual",
      "meteringMode": "Pattern",
      "flash": "关闭",
      "brightness": "-2.67",
      "exposureBias": "0 EV",
      "sensingMethod": "-",
      "gps": null
    }
  },
  {
    "id": "uvd8rk60j",
    "url": "photos/青甘大环线/1725193884000.jpeg",
    "thumb": "thumbs/青甘大环线/1725193884000.jpeg",
    "name": "1725193884000.jpeg",
    "category": "青甘大环线",
    "date": "2024-09-01T12:31:24.000Z",
    "size": "13.59 MB",
    "width": 7952,
    "height": 4472,
    "exif": {
      "make": "SONY",
      "model": "ILCE-7RM2",
      "software": "ILCE-7RM2 v3.30",
      "focal": "50mm",
      "fstop": "f/1.8",
      "iso": "50",
      "shutter": "1/200",
      "lens": "YN50mm f/1.8S DF DSM",
      "focal35": "50mm",
      "whiteBalance": "Auto",
      "exposureProgram": "Manual",
      "meteringMode": "Pattern",
      "flash": "关闭",
      "brightness": "3.10",
      "exposureBias": "0 EV",
      "sensingMethod": "-",
      "gps": null
    }
  },
  {
    "id": "b57bg0orr",
    "url": "photos/苏州/1681633973458.jpeg",
    "thumb": "thumbs/苏州/1681633973458.jpeg",
    "name": "1681633973458.jpeg",
    "category": "苏州",
    "date": "2023-08-06T07:06:36.000Z",
    "size": "839.02 KB",
    "width": 1203,
    "height": 1882,
    "exif": {
      "make": "",
      "model": "",
      "software": "-",
      "focal": "-",
      "fstop": "-",
      "iso": "-",
      "shutter": "-",
      "lens": "-",
      "focal35": "-",
      "whiteBalance": "-",
      "exposureProgram": "-",
      "meteringMode": "-",
      "flash": "-",
      "brightness": "-",
      "exposureBias": "0 EV",
      "sensingMethod": "-",
      "gps": null
    }
  },
  {
    "id": "uqeww4tmr",
    "url": "photos/苏州/1681634373003.jpeg",
    "thumb": "thumbs/苏州/1681634373003.jpeg",
    "name": "1681634373003.jpeg",
    "category": "苏州",
    "date": "2023-08-06T07:06:12.000Z",
    "size": "3.43 MB",
    "width": 4032,
    "height": 3024,
    "exif": {
      "make": "",
      "model": "",
      "software": "-",
      "focal": "-",
      "fstop": "-",
      "iso": "-",
      "shutter": "-",
      "lens": "-",
      "focal35": "-",
      "whiteBalance": "-",
      "exposureProgram": "-",
      "meteringMode": "-",
      "flash": "-",
      "brightness": "-",
      "exposureBias": "0 EV",
      "sensingMethod": "-",
      "gps": null
    }
  },
  {
    "id": "1lywme35c",
    "url": "photos/莫干山/1691297259277.heic",
    "thumb": "thumbs/莫干山/1691297259277.heic",
    "name": "1691297259277.heic",
    "category": "莫干山",
    "date": "2023-08-06T04:47:39.000Z",
    "size": "2.13 MB",
    "width": 4032,
    "height": 3024,
    "exif": {
      "make": "Apple",
      "model": "iPhone 14",
      "software": "16.4.1",
      "focal": "6mm",
      "fstop": "f/1.5",
      "iso": "100",
      "shutter": "1/121",
      "lens": "iPhone 14 back dual wide camera 5.7mm f/1.5",
      "focal35": "63mm",
      "whiteBalance": "Auto",
      "exposureProgram": "Normal program",
      "meteringMode": "Spot",
      "flash": "关闭",
      "brightness": "3.95",
      "exposureBias": "0 EV",
      "sensingMethod": "One-chip color area sensor",
      "gps": {
        "lat": 30.60728055555556,
        "lng": 119.86719444444444
      }
    }
  },
  {
    "id": "x7575chnu",
    "url": "photos/莫干山/1691292043209.heic",
    "thumb": "thumbs/莫干山/1691292043209.heic",
    "name": "1691292043209.heic",
    "category": "莫干山",
    "date": "2023-08-06T03:20:43.000Z",
    "size": "1.79 MB",
    "width": 4032,
    "height": 3024,
    "exif": {
      "make": "Apple",
      "model": "iPhone 14",
      "software": "16.4.1",
      "focal": "6mm",
      "fstop": "f/1.5",
      "iso": "50",
      "shutter": "1/1238",
      "lens": "iPhone 14 back dual wide camera 5.7mm f/1.5",
      "focal35": "26mm",
      "whiteBalance": "Auto",
      "exposureProgram": "Normal program",
      "meteringMode": "Spot",
      "flash": "关闭",
      "brightness": "8.32",
      "exposureBias": "0 EV",
      "sensingMethod": "One-chip color area sensor",
      "gps": {
        "lat": 30.610541666666666,
        "lng": 119.84811388888889
      }
    }
  },
  {
    "id": "jaa2iqi6n",
    "url": "photos/莫干山/1691287762254.heic",
    "thumb": "thumbs/莫干山/1691287762254.heic",
    "name": "1691287762254.heic",
    "category": "莫干山",
    "date": "2023-08-06T02:09:22.000Z",
    "size": "1.61 MB",
    "width": 4032,
    "height": 3024,
    "exif": {
      "make": "Apple",
      "model": "iPhone 14",
      "software": "16.4.1",
      "focal": "6mm",
      "fstop": "f/1.5",
      "iso": "64",
      "shutter": "1/121",
      "lens": "iPhone 14 back dual wide camera 5.7mm f/1.5",
      "focal35": "36mm",
      "whiteBalance": "Auto",
      "exposureProgram": "Normal program",
      "meteringMode": "Pattern",
      "flash": "关闭",
      "brightness": "4.32",
      "exposureBias": "0 EV",
      "sensingMethod": "One-chip color area sensor",
      "gps": {
        "lat": 30.60855,
        "lng": 119.86207499999999
      }
    }
  },
  {
    "id": "q12xbotj9",
    "url": "photos/莫干山/1691284882257.heic",
    "thumb": "thumbs/莫干山/1691284882257.heic",
    "name": "1691284882257.heic",
    "category": "莫干山",
    "date": "2023-08-06T01:21:22.000Z",
    "size": "966.09 KB",
    "width": 4032,
    "height": 3024,
    "exif": {
      "make": "Apple",
      "model": "iPhone 14",
      "software": "16.4.1",
      "focal": "6mm",
      "fstop": "f/1.5",
      "iso": "50",
      "shutter": "1/5587",
      "lens": "iPhone 14 back dual wide camera 5.7mm f/1.5",
      "focal35": "26mm",
      "whiteBalance": "Auto",
      "exposureProgram": "Normal program",
      "meteringMode": "Spot",
      "flash": "关闭",
      "brightness": "10.63",
      "exposureBias": "0 EV",
      "sensingMethod": "One-chip color area sensor",
      "gps": {
        "lat": 30.61548888888889,
        "lng": 119.87011666666666
      }
    }
  },
  {
    "id": "f6rogl9f1",
    "url": "photos/莫干山/1691284169034.heic",
    "thumb": "thumbs/莫干山/1691284169034.heic",
    "name": "1691284169034.heic",
    "category": "莫干山",
    "date": "2023-08-06T01:09:29.000Z",
    "size": "1.42 MB",
    "width": 4032,
    "height": 3024,
    "exif": {
      "make": "Apple",
      "model": "iPhone 14",
      "software": "16.4.1",
      "focal": "6mm",
      "fstop": "f/1.5",
      "iso": "50",
      "shutter": "1/100",
      "lens": "iPhone 14 back dual wide camera 5.7mm f/1.5",
      "focal35": "60mm",
      "whiteBalance": "Auto",
      "exposureProgram": "Normal program",
      "meteringMode": "Pattern",
      "flash": "关闭",
      "brightness": "4.61",
      "exposureBias": "0 EV",
      "sensingMethod": "One-chip color area sensor",
      "gps": {
        "lat": 30.614972222222224,
        "lng": 119.86943055555555
      }
    }
  },
  {
    "id": "00iwjpqjr",
    "url": "photos/莫干山/1691218072569.jpeg",
    "thumb": "thumbs/莫干山/1691218072569.jpeg",
    "name": "1691218072569.jpeg",
    "category": "莫干山",
    "date": "2023-08-05T06:47:52.000Z",
    "size": "2.85 MB",
    "width": 4030,
    "height": 2627,
    "exif": {
      "make": "Apple",
      "model": "iPhone 14",
      "software": "Snapseed 2.22.412829873",
      "focal": "6mm",
      "fstop": "f/1.5",
      "iso": "40",
      "shutter": "1/282",
      "lens": "iPhone 14 back dual wide camera 5.7mm f/1.5",
      "focal35": "59mm",
      "whiteBalance": "Auto",
      "exposureProgram": "Normal program",
      "meteringMode": "Spot",
      "flash": "关闭",
      "brightness": "5.57",
      "exposureBias": "0 EV",
      "sensingMethod": "One-chip color area sensor",
      "gps": {
        "lat": 30.53861666666667,
        "lng": 119.95316944444444
      }
    }
  },
  {
    "id": "qqg7d35up",
    "url": "photos/莫干山/1691209298837.jpeg",
    "thumb": "thumbs/莫干山/1691209298837.jpeg",
    "name": "1691209298837.jpeg",
    "category": "莫干山",
    "date": "2023-08-05T04:21:38.000Z",
    "size": "2.11 MB",
    "width": 3913,
    "height": 3024,
    "exif": {
      "make": "Apple",
      "model": "iPhone 14",
      "software": "Snapseed 2.22.412829873",
      "focal": "6mm",
      "fstop": "f/1.5",
      "iso": "50",
      "shutter": "1/2632",
      "lens": "iPhone 14 back dual wide camera 5.7mm f/1.5",
      "focal35": "54mm",
      "whiteBalance": "Auto",
      "exposureProgram": "Normal program",
      "meteringMode": "Pattern",
      "flash": "关闭",
      "brightness": "9.48",
      "exposureBias": "0 EV",
      "sensingMethod": "One-chip color area sensor",
      "gps": {
        "lat": 30.5195,
        "lng": 120.51248888888888
      }
    }
  },
  {
    "id": "iuhki67st",
    "url": "photos/苏州/1681561661766.heic",
    "thumb": "thumbs/苏州/1681561661766.heic",
    "name": "1681561661766.heic",
    "category": "苏州",
    "date": "2023-04-15T12:27:41.000Z",
    "size": "1.21 MB",
    "width": 4032,
    "height": 3024,
    "exif": {
      "make": "Apple",
      "model": "iPhone 14",
      "software": "16.3.1",
      "focal": "6mm",
      "fstop": "f/1.5",
      "iso": "640",
      "shutter": "1/11",
      "lens": "iPhone 14 back dual wide camera 5.7mm f/1.5",
      "focal35": "26mm",
      "whiteBalance": "Auto",
      "exposureProgram": "Normal program",
      "meteringMode": "Pattern",
      "flash": "关闭",
      "brightness": "-3.39",
      "exposureBias": "0 EV",
      "sensingMethod": "One-chip color area sensor",
      "gps": null
    }
  },
  {
    "id": "7ggmcaqi7",
    "url": "photos/苏州/IMG_4618.HEIC.heic",
    "thumb": "thumbs/苏州/IMG_4618.HEIC.heic",
    "name": "IMG_4618.HEIC.heic",
    "category": "苏州",
    "date": "2023-04-15T12:20:28.000Z",
    "size": "1.62 MB",
    "width": 4032,
    "height": 3024,
    "exif": {
      "make": "Apple",
      "model": "iPhone 14",
      "software": "16.3.1",
      "focal": "6mm",
      "fstop": "f/1.5",
      "iso": "400",
      "shutter": "1/33",
      "lens": "iPhone 14 back dual wide camera 5.7mm f/1.5",
      "focal35": "26mm",
      "whiteBalance": "Auto",
      "exposureProgram": "Normal program",
      "meteringMode": "Pattern",
      "flash": "关闭",
      "brightness": "-0.28",
      "exposureBias": "0 EV",
      "sensingMethod": "One-chip color area sensor",
      "gps": null
    }
  },
  {
    "id": "3582n23w8",
    "url": "photos/苏州/IMG_4617.HEIC.heic",
    "thumb": "thumbs/苏州/IMG_4617.HEIC.heic",
    "name": "IMG_4617.HEIC.heic",
    "category": "苏州",
    "date": "2023-04-15T08:28:42.000Z",
    "size": "2.44 MB",
    "width": 4032,
    "height": 3024,
    "exif": {
      "make": "Apple",
      "model": "iPhone 14 Pro Max",
      "software": "16.3.1",
      "focal": "7mm",
      "fstop": "f/1.78",
      "iso": "80",
      "shutter": "1/521",
      "lens": "iPhone 14 Pro Max back triple camera 6.86mm f/1.78",
      "focal35": "24mm",
      "whiteBalance": "Auto",
      "exposureProgram": "Normal program",
      "meteringMode": "Pattern",
      "flash": "关闭",
      "brightness": "6.69",
      "exposureBias": "0 EV",
      "sensingMethod": "One-chip color area sensor",
      "gps": {
        "lat": 31.3137,
        "lng": 120.63018055555555
      }
    }
  },
  {
    "id": "qncaakvr3",
    "url": "photos/苏州/IMG_4608.HEIC.heic",
    "thumb": "thumbs/苏州/IMG_4608.HEIC.heic",
    "name": "IMG_4608.HEIC.heic",
    "category": "苏州",
    "date": "2023-04-15T07:38:17.000Z",
    "size": "954.05 KB",
    "width": 4032,
    "height": 3024,
    "exif": {
      "make": "Apple",
      "model": "iPhone 14 Pro Max",
      "software": "16.3.1",
      "focal": "7mm",
      "fstop": "f/1.78",
      "iso": "64",
      "shutter": "1/880",
      "lens": "iPhone 14 Pro Max back triple camera 6.86mm f/1.78",
      "focal35": "61mm",
      "whiteBalance": "Auto",
      "exposureProgram": "Normal program",
      "meteringMode": "Pattern",
      "flash": "关闭",
      "brightness": "7.89",
      "exposureBias": "0 EV",
      "sensingMethod": "One-chip color area sensor",
      "gps": {
        "lat": 31.31426111111111,
        "lng": 120.62958611111111
      }
    }
  },
  {
    "id": "0p9c1kdow",
    "url": "photos/苏州/IMG_4601.HEIC.heic",
    "thumb": "thumbs/苏州/IMG_4601.HEIC.heic",
    "name": "IMG_4601.HEIC.heic",
    "category": "苏州",
    "date": "2023-04-15T07:31:52.000Z",
    "size": "1.93 MB",
    "width": 4032,
    "height": 3024,
    "exif": {
      "make": "Apple",
      "model": "iPhone 14 Pro Max",
      "software": "16.3.1",
      "focal": "7mm",
      "fstop": "f/1.78",
      "iso": "80",
      "shutter": "1/1916",
      "lens": "iPhone 14 Pro Max back triple camera 6.86mm f/1.78",
      "focal35": "24mm",
      "whiteBalance": "Auto",
      "exposureProgram": "Normal program",
      "meteringMode": "Pattern",
      "flash": "关闭",
      "brightness": "8.75",
      "exposureBias": "0 EV",
      "sensingMethod": "One-chip color area sensor",
      "gps": {
        "lat": 31.313866666666666,
        "lng": 120.62748055555555
      }
    }
  },
  {
    "id": "9qtjd7v45",
    "url": "photos/苏州/IMG_4596.HEIC.heic",
    "thumb": "thumbs/苏州/IMG_4596.HEIC.heic",
    "name": "IMG_4596.HEIC.heic",
    "category": "苏州",
    "date": "2023-04-15T07:14:00.000Z",
    "size": "1.35 MB",
    "width": 4032,
    "height": 3024,
    "exif": {
      "make": "Apple",
      "model": "iPhone 14 Pro Max",
      "software": "16.3.1",
      "focal": "7mm",
      "fstop": "f/1.78",
      "iso": "80",
      "shutter": "1/339",
      "lens": "iPhone 14 Pro Max back triple camera 6.86mm f/1.78",
      "focal35": "24mm",
      "whiteBalance": "Auto",
      "exposureProgram": "Normal program",
      "meteringMode": "Pattern",
      "flash": "关闭",
      "brightness": "5.91",
      "exposureBias": "0 EV",
      "sensingMethod": "One-chip color area sensor",
      "gps": {
        "lat": 31.313433333333332,
        "lng": 120.62566388888888
      }
    }
  },
  {
    "id": "3x36u0l0u",
    "url": "photos/上海动物园/1676712685522.jpeg",
    "thumb": "thumbs/上海动物园/1676712685522.jpeg",
    "name": "1676712685522.jpeg",
    "category": "上海动物园",
    "date": "2023-02-19T02:41:22.000Z",
    "size": "6.96 MB",
    "width": 3024,
    "height": 4032,
    "exif": {
      "make": "",
      "model": "",
      "software": "-",
      "focal": "-",
      "fstop": "-",
      "iso": "-",
      "shutter": "-",
      "lens": "-",
      "focal35": "-",
      "whiteBalance": "-",
      "exposureProgram": "-",
      "meteringMode": "-",
      "flash": "-",
      "brightness": "-",
      "exposureBias": "0 EV",
      "sensingMethod": "-",
      "gps": null
    }
  },
  {
    "id": "u1y9hy0nf",
    "url": "photos/上海动物园/1676714009017.jpeg",
    "thumb": "thumbs/上海动物园/1676714009017.jpeg",
    "name": "1676714009017.jpeg",
    "category": "上海动物园",
    "date": "2023-02-19T02:40:42.000Z",
    "size": "6.79 MB",
    "width": 4032,
    "height": 3024,
    "exif": {
      "make": "",
      "model": "",
      "software": "-",
      "focal": "-",
      "fstop": "-",
      "iso": "-",
      "shutter": "-",
      "lens": "-",
      "focal35": "-",
      "whiteBalance": "-",
      "exposureProgram": "-",
      "meteringMode": "-",
      "flash": "-",
      "brightness": "-",
      "exposureBias": "0 EV",
      "sensingMethod": "-",
      "gps": null
    }
  },
  {
    "id": "5zea6rej1",
    "url": "photos/上海动物园/1676713145227.jpeg",
    "thumb": "thumbs/上海动物园/1676713145227.jpeg",
    "name": "1676713145227.jpeg",
    "category": "上海动物园",
    "date": "2023-02-19T02:40:12.000Z",
    "size": "948.59 KB",
    "width": 1920,
    "height": 1080,
    "exif": {
      "make": "",
      "model": "",
      "software": "-",
      "focal": "-",
      "fstop": "-",
      "iso": "-",
      "shutter": "-",
      "lens": "-",
      "focal35": "-",
      "whiteBalance": "-",
      "exposureProgram": "-",
      "meteringMode": "-",
      "flash": "-",
      "brightness": "-",
      "exposureBias": "0 EV",
      "sensingMethod": "-",
      "gps": null
    }
  },
  {
    "id": "os9jie5io",
    "url": "photos/上海动物园/1676714054512.jpeg",
    "thumb": "thumbs/上海动物园/1676714054512.jpeg",
    "name": "1676714054512.jpeg",
    "category": "上海动物园",
    "date": "2023-02-19T02:39:54.000Z",
    "size": "4.06 MB",
    "width": 3024,
    "height": 4032,
    "exif": {
      "make": "",
      "model": "",
      "software": "-",
      "focal": "-",
      "fstop": "-",
      "iso": "-",
      "shutter": "-",
      "lens": "-",
      "focal35": "-",
      "whiteBalance": "-",
      "exposureProgram": "-",
      "meteringMode": "-",
      "flash": "-",
      "brightness": "-",
      "exposureBias": "0 EV",
      "sensingMethod": "-",
      "gps": null
    }
  },
  {
    "id": "ebciv3lcg",
    "url": "photos/上海动物园/IMG_3745.HEIC.heic",
    "thumb": "thumbs/上海动物园/IMG_3745.HEIC.heic",
    "name": "IMG_3745.HEIC.heic",
    "category": "上海动物园",
    "date": "2023-02-18T09:14:49.000Z",
    "size": "1.89 MB",
    "width": 4032,
    "height": 3024,
    "exif": {
      "make": "Apple",
      "model": "iPhone 14",
      "software": "16.1.2",
      "focal": "6mm",
      "fstop": "f/1.5",
      "iso": "100",
      "shutter": "1/121",
      "lens": "iPhone 14 back dual wide camera 5.7mm f/1.5",
      "focal35": "27mm",
      "whiteBalance": "Auto",
      "exposureProgram": "Normal program",
      "meteringMode": "Spot",
      "flash": "关闭",
      "brightness": "4.01",
      "exposureBias": "0 EV",
      "sensingMethod": "One-chip color area sensor",
      "gps": null
    }
  },
  {
    "id": "n9hhca07y",
    "url": "photos/上海动物园/IMG_3693.HEIC.heic",
    "thumb": "thumbs/上海动物园/IMG_3693.HEIC.heic",
    "name": "IMG_3693.HEIC.heic",
    "category": "上海动物园",
    "date": "2023-02-18T08:03:04.000Z",
    "size": "4.14 MB",
    "width": 4032,
    "height": 3024,
    "exif": {
      "make": "Apple",
      "model": "iPhone 14",
      "software": "16.1.2",
      "focal": "6mm",
      "fstop": "f/1.5",
      "iso": "50",
      "shutter": "1/567",
      "lens": "iPhone 14 back dual wide camera 5.7mm f/1.5",
      "focal35": "26mm",
      "whiteBalance": "Auto",
      "exposureProgram": "Normal program",
      "meteringMode": "Pattern",
      "flash": "关闭",
      "brightness": "7.14",
      "exposureBias": "0 EV",
      "sensingMethod": "One-chip color area sensor",
      "gps": null
    }
  },
  {
    "id": "2ow1lgud0",
    "url": "photos/上海动物园/IMG_3643.HEIC.heic",
    "thumb": "thumbs/上海动物园/IMG_3643.HEIC.heic",
    "name": "IMG_3643.HEIC.heic",
    "category": "上海动物园",
    "date": "2023-02-18T06:43:32.000Z",
    "size": "1.31 MB",
    "width": 4032,
    "height": 3024,
    "exif": {
      "make": "Apple",
      "model": "iPhone 14",
      "software": "16.1.2",
      "focal": "6mm",
      "fstop": "f/1.5",
      "iso": "50",
      "shutter": "1/2045",
      "lens": "iPhone 14 back dual wide camera 5.7mm f/1.5",
      "focal35": "26mm",
      "whiteBalance": "Auto",
      "exposureProgram": "Normal program",
      "meteringMode": "Pattern",
      "flash": "关闭",
      "brightness": "9.04",
      "exposureBias": "0 EV",
      "sensingMethod": "One-chip color area sensor",
      "gps": null
    }
  },
  {
    "id": "e6wxv1j9a",
    "url": "photos/上海动物园/IMG_3631.HEIC.heic",
    "thumb": "thumbs/上海动物园/IMG_3631.HEIC.heic",
    "name": "IMG_3631.HEIC.heic",
    "category": "上海动物园",
    "date": "2023-02-18T06:30:09.000Z",
    "size": "1.81 MB",
    "width": 4032,
    "height": 3024,
    "exif": {
      "make": "Apple",
      "model": "iPhone 14",
      "software": "16.1.2",
      "focal": "6mm",
      "fstop": "f/1.5",
      "iso": "125",
      "shutter": "1/121",
      "lens": "iPhone 14 back dual wide camera 5.7mm f/1.5",
      "focal35": "32mm",
      "whiteBalance": "Auto",
      "exposureProgram": "Normal program",
      "meteringMode": "Spot",
      "flash": "关闭",
      "brightness": "3.34",
      "exposureBias": "0 EV",
      "sensingMethod": "One-chip color area sensor",
      "gps": null
    }
  },
  {
    "id": "oobov864z",
    "url": "photos/上海动物园/IMG_3630.HEIC.heic",
    "thumb": "thumbs/上海动物园/IMG_3630.HEIC.heic",
    "name": "IMG_3630.HEIC.heic",
    "category": "上海动物园",
    "date": "2023-02-18T06:25:02.000Z",
    "size": "3.27 MB",
    "width": 4032,
    "height": 3024,
    "exif": {
      "make": "Apple",
      "model": "iPhone 14",
      "software": "16.1.2",
      "focal": "6mm",
      "fstop": "f/1.5",
      "iso": "50",
      "shutter": "1/121",
      "lens": "iPhone 14 back dual wide camera 5.7mm f/1.5",
      "focal35": "26mm",
      "whiteBalance": "Auto",
      "exposureProgram": "Normal program",
      "meteringMode": "Pattern",
      "flash": "关闭",
      "brightness": "4.84",
      "exposureBias": "0 EV",
      "sensingMethod": "One-chip color area sensor",
      "gps": null
    }
  },
  {
    "id": "zkri8yvd6",
    "url": "photos/上海动物园/IMG_3622.HEIC.heic",
    "thumb": "thumbs/上海动物园/IMG_3622.HEIC.heic",
    "name": "IMG_3622.HEIC.heic",
    "category": "上海动物园",
    "date": "2023-02-18T06:21:03.000Z",
    "size": "2.99 MB",
    "width": 4032,
    "height": 3024,
    "exif": {
      "make": "Apple",
      "model": "iPhone 14",
      "software": "16.1.2",
      "focal": "6mm",
      "fstop": "f/1.5",
      "iso": "50",
      "shutter": "1/1344",
      "lens": "iPhone 14 back dual wide camera 5.7mm f/1.5",
      "focal35": "26mm",
      "whiteBalance": "Auto",
      "exposureProgram": "Normal program",
      "meteringMode": "Pattern",
      "flash": "关闭",
      "brightness": "8.35",
      "exposureBias": "0 EV",
      "sensingMethod": "One-chip color area sensor",
      "gps": null
    }
  }
]